src/cli/__init__.py
src/cli/quick_commit.py
src/cli/sync.py
src/git_utils/__init__.py
src/git_utils/commands.py
src/main.py
src/utils/__init__.py
src/utils/helpers.py
src/utils/logging.py
easy_git_cli-0.3.0.dist-info/LICENSE
easy_git_cli-0.3.0.dist-info/METADATA
easy_git_cli-0.3.0.dist-info/WHEEL
easy_git_cli-0.3.0.dist-info/entry_points.txt
easy_git_cli-0.3.0.dist-info/RECORD
