Metadata-Version: 2.1
Name: easy-git-cli
Version: 0.3.0
Summary: A CLI tool to simplify Git workflows
License: MIT
Author: Omar Allouch
Author-email: allouchomar1@gmail.com
Requires-Python: >=3.12,<4.0
Classifier: License :: OSI Approved :: MIT License
Classifier: Programming Language :: Python :: 3
Classifier: Programming Language :: Python :: 3.12
Requires-Dist: click (>=8.1.7,<9.0.0)
Requires-Dist: gitpython (>=3.1.43,<4.0.0)
Requires-Dist: pre-commit (>=4.0.1,<5.0.0)
Requires-Dist: questionary (>=2.0.1,<3.0.0)
Requires-Dist: ruff (>=0.8.2,<0.9.0)
